mehdashti_observability/__init__.py
mehdashti_observability/correlation.py
mehdashti_observability/health.py
mehdashti_observability/py.typed
mehdashti_observability-0.2.0.dist-info/METADATA
mehdashti_observability-0.2.0.dist-info/WHEEL
mehdashti_observability-0.2.0.dist-info/RECORD
