Metadata-Version: 2.4
Name: mehdashti-observability
Version: 0.2.0
Summary: Observability utilities for Smart Platform - correlation IDs, health checks, and request tracing
Project-URL: Homepage, https://github.com/mehdashti/smart-platform
Project-URL: Repository, https://github.com/mehdashti/smart-platform.git
Project-URL: Issues, https://github.com/mehdashti/smart-platform/issues
Author: mehdashti
License: MIT
Keywords: correlation-id,fastapi,health-checks,middleware,observability
Classifier: Development Status :: 4 - Beta
Classifier: Framework :: FastAPI
Classifier: Intended Audience :: Developers
Classifier: License :: OSI Approved :: MIT License
Classifier: Programming Language :: Python :: 3
Classifier: Programming Language :: Python :: 3.13
Requires-Python: >=3.13
Requires-Dist: fastapi>=0.115.0
Requires-Dist: pydantic>=2.10.0
Requires-Dist: starlette>=0.41.0
Requires-Dist: uuid-utils>=0.9.0
